{
    "0.02_APX": [
        [
            1236.0,
            5.67
        ],
        [
            1073.0,
            5.81
        ],
        [
            954.0,
            5.94
        ],
        [
            899.0,
            6.11
        ],
        [
            856.91,
            6.32
        ],
        [
            818.32,
            6.56
        ],
        [
            782.69,
            6.79
        ],
        [
            727.0,
            6.98
        ],
        [
            687.0,
            7.19
        ],
        [
            666.0,
            7.34
        ]
    ],
    "0.02_APX2": [
        [
            1236.0,
            5.67
        ],
        [
            1211.76,
            5.7
        ],
        [
            1073.0,
            5.81
        ],
        [
            1051.96,
            5.83
        ],
        [
            954.0,
            5.94
        ],
        [
            935.29,
            5.99
        ],
        [
            899.0,
            6.11
        ],
        [
            881.37,
            6.2
        ],
        [
            856.91,
            6.32
        ],
        [
            840.11,
            6.43
        ],
        [
            818.32,
            6.56
        ],
        [
            802.27,
            6.66
        ],
        [
            782.69,
            6.79
        ],
        [
            767.34,
            6.84
        ],
        [
            727.0,
            6.98
        ],
        [
            712.75,
            7.05
        ],
        [
            687.0,
            7.19
        ],
        [
            667.87,
            7.28
        ],
        [
            666.0,
            7.34
        ]
    ],
    "0.02_APX_time": 713.9286839962006,
    "0.02_APX_gap": 0.0,
    "0.03_APX": [
        [
            1183.0,
            5.73
        ],
        [
            982.0,
            5.91
        ],
        [
            897.34,
            6.13
        ],
        [
            837.27,
            6.45
        ],
        [
            784.0,
            6.79
        ],
        [
            706.0,
            7.07
        ],
        [
            666.0,
            7.32
        ]
    ],
    "0.03_APX2": [
        [
            1183.0,
            5.73
        ],
        [
            1148.54,
            5.74
        ],
        [
            982.0,
            5.91
        ],
        [
            953.4,
            5.95
        ],
        [
            897.34,
            6.13
        ],
        [
            871.2,
            6.26
        ],
        [
            837.27,
            6.45
        ],
        [
            812.88,
            6.59
        ],
        [
            784.0,
            6.79
        ],
        [
            761.17,
            6.86
        ],
        [
            706.0,
            7.07
        ],
        [
            685.44,
            7.2
        ],
        [
            666.0,
            7.32
        ]
    ],
    "0.03_APX_time": 97.18045902252197,
    "0.03_APX_gap": 0.0,
    "EI_0.02_APX": 0.018996100138382044,
    "EI_0.02_APX2": 0.018996100138382044,
    "EI_0.03_APX": 0.02977912765307411,
    "EI_0.03_APX2": 0.02977912765307411
}